setup.py
cli2web/__init__.py
cli2web.egg-info/PKG-INFO
cli2web.egg-info/SOURCES.txt
cli2web.egg-info/dependency_links.txt
cli2web.egg-info/entry_points.txt
cli2web.egg-info/requires.txt
cli2web.egg-info/top_level.txt
cli2web/templates/cli.html
cli2web/templates/dir.html
cli2web/templates/job.tpl.sh
cli2web/templates/overview.html