Metadata-Version: 1.0
Name: cli2web
Version: 0.1
Summary: Wraps cli applications to web services
Home-page: https://github.com/CognitionGuidedSurgery/cli2web
Author: Alexander Weigl
Author-email: Alexander.Weigl@student.kit.edu
License: UNKNOWN
Platform: UNKNOWN
